micronets/__init__.py
micronets/autograd_engine.py
micronets/graph.py
micronets/losses.py
micronets/nn.py
micronets-0.1.2.dist-info/LICENSE
micronets-0.1.2.dist-info/METADATA
micronets-0.1.2.dist-info/WHEEL
micronets-0.1.2.dist-info/top_level.txt
micronets-0.1.2.dist-info/RECORD
