Metadata-Version: 2.1
Name: micronets
Version: 0.1.2
Summary: A simple autograd engine along with a PyTorch/Tensorflow like API module to easily train neural nets
Author-email: Sarthak Rawat <hare.sarthak@gmail.com>
Project-URL: Homepage, https://github.com/Sarthakrw/micronets
Project-URL: Bug Tracker, https://github.com/Sarthakrw/micronets/issues
Classifier: Programming Language :: Python :: 3
Classifier: License :: OSI Approved :: MIT License
Classifier: Operating System :: OS Independent
Requires-Python: >=3.7
License-File: LICENSE
Requires-Dist: matplotlib >=3.7.0
Requires-Dist: graphviz >=0.20.0
